noahs_camera_controller/__init__.py
noahs_camera_controller/camera.py
noahs_camera_controller-0.1.0.dist-info/METADATA
noahs_camera_controller-0.1.0.dist-info/WHEEL
noahs_camera_controller-0.1.0.dist-info/top_level.txt
noahs_camera_controller-0.1.0.dist-info/RECORD
